README.md
setup.cfg
setup.py
animality/__init__.py
animality/cli.py
animality/lib.py
animality_py.egg-info/PKG-INFO
animality_py.egg-info/SOURCES.txt
animality_py.egg-info/dependency_links.txt
animality_py.egg-info/entry_points.txt
animality_py.egg-info/requires.txt
animality_py.egg-info/top_level.txt