Metadata-Version: 2.1
Name: animality-py
Version: 0.1.2
Summary: A python API wrapper for https://animality.xyz
Home-page: https://github.com/animal-api/animality-py
Author: vierofernando
Author-email: vierofernando9@gmail.com
License: MIT
Download-URL: https://github.com/animal-api/animality-py/archive/0.1.2.tar.gz
Keywords: Animals,API,Hamburger,Pats,Headpats,API Wrapper
Platform: UNKNOWN
Classifier: Development Status :: 4 - Beta
Classifier: Intended Audience :: Developers
Classifier: Topic :: Software Development :: Build Tools
Classifier: License :: OSI Approved :: MIT License
Classifier: Programming Language :: Python :: 3.7
Classifier: Programming Language :: Python :: 3.8
Classifier: Programming Language :: Python :: 3.9
Requires-Python: >=3.7
